{
  "bodies": [
    {
      "name": "P1",
      "mass_kg": 1,
      "diam_m": 0.01,
      "init_vel_x_ms": 0.39295,
      "init_vel_y_ms": 0.09758,
      "init_pos_x_m": 4,
      "init_pos_y_m": 5
    },
    {
      "name": "P2",
      "mass_kg": 1,
      "diam_m": 0.01,
      "init_vel_x_ms": 0.39295,
      "init_vel_y_ms": 0.09758,
      "init_pos_x_m": 6,
      "init_pos_y_m": 5

    },
    {
      "name": "P3",
      "mass_kg": 1,
      "diam_m": 0.01,
      "init_vel_x_ms": -0.7859,
      "init_vel_y_ms": -0.19516,
      "init_pos_x_m": 5,
      "init_pos_y_m": 5

    }
  ],
  "globals": {
    "sim_dim_x_m": 10,
    "sim_dim_y_m": 10,
    "time_step_s": 0.002,
    "sim_duration_s":25
  } 
}
